LICENSE
MANIFEST.in
README.md
setup.cfg
setup.py
google_compute_engine/__init__.py
google_compute_engine/compat.py
google_compute_engine/config_manager.py
google_compute_engine/constants.py
google_compute_engine/file_utils.py
google_compute_engine/logger.py
google_compute_engine/metadata_watcher.py
google_compute_engine/network_utils.py
google_compute_engine/test_compat.py
google_compute_engine.egg-info/PKG-INFO
google_compute_engine.egg-info/SOURCES.txt
google_compute_engine.egg-info/dependency_links.txt
google_compute_engine.egg-info/entry_points.txt
google_compute_engine.egg-info/requires.txt
google_compute_engine.egg-info/top_level.txt
google_compute_engine/accounts/__init__.py
google_compute_engine/accounts/accounts_daemon.py
google_compute_engine/accounts/accounts_utils.py
google_compute_engine/accounts/oslogin_utils.py
google_compute_engine/boto/__init__.py
google_compute_engine/boto/boto_config.py
google_compute_engine/boto/compute_auth.py
google_compute_engine/clock_skew/__init__.py
google_compute_engine/clock_skew/clock_skew_daemon.py
google_compute_engine/distro/__init__.py
google_compute_engine/distro/helpers.py
google_compute_engine/distro/utils.py
google_compute_engine/distro/debian_8/__init__.py
google_compute_engine/distro/debian_8/utils.py
google_compute_engine/distro/debian_8/tests/__init__.py
google_compute_engine/distro/debian_8/tests/utils_test.py
google_compute_engine/distro/debian_9/__init__.py
google_compute_engine/distro/debian_9/utils.py
google_compute_engine/distro/debian_9/tests/__init__.py
google_compute_engine/distro/debian_9/tests/utils_test.py
google_compute_engine/distro/el_6/__init__.py
google_compute_engine/distro/el_6/utils.py
google_compute_engine/distro/el_6/tests/__init__.py
google_compute_engine/distro/el_6/tests/utils_test.py
google_compute_engine/distro/el_7/__init__.py
google_compute_engine/distro/el_7/utils.py
google_compute_engine/distro/el_7/tests/__init__.py
google_compute_engine/distro/el_7/tests/utils_test.py
google_compute_engine/distro/sles_11/__init__.py
google_compute_engine/distro/sles_11/utils.py
google_compute_engine/distro/sles_11/tests/__init__.py
google_compute_engine/distro/sles_11/tests/utils_test.py
google_compute_engine/distro/sles_12/__init__.py
